codehackscalculator/__init__.py
ridaCalculatrice-0.0.1.dist-info/LICENSE.txt
ridaCalculatrice-0.0.1.dist-info/METADATA
ridaCalculatrice-0.0.1.dist-info/WHEEL
ridaCalculatrice-0.0.1.dist-info/top_level.txt
ridaCalculatrice-0.0.1.dist-info/RECORD
